FREEZINGEYES_STT/__init__.py
FREEZINGEYES_STT-1.0.3.dist-info/METADATA
FREEZINGEYES_STT-1.0.3.dist-info/WHEEL
FREEZINGEYES_STT-1.0.3.dist-info/top_level.txt
FREEZINGEYES_STT-1.0.3.dist-info/RECORD
