Metadata-Version: 2.1
Name: FREEZINGEYES_STT
Version: 1.0.3
Summary: Contain only one command which is > listen() > It just listenss
Author: FreezingEYES
Author-email: manthanrauthan1@gmail.com
